gamechanger/__init__.py
gamechanger/main.py
gamechanger-1.0.dist-info/LICENSE
gamechanger-1.0.dist-info/METADATA
gamechanger-1.0.dist-info/WHEEL
gamechanger-1.0.dist-info/top_level.txt
gamechanger-1.0.dist-info/RECORD
