Metadata-Version: 2.1
Name: gamechanger
Version: 1.0
Summary: A sample gamechanger library for gamification
Home-page: https://github.com/abdellatif-belmady/gamechanger
Author: Abdellatif BELMADY
Author-email: <abdellatif.belmady@gmail.com>
License-File: LICENSE
